colemen_file_utils.py
dir.py
file.py
file_read.py
file_search.py
file_write.py
objectUtils.py
string_utils.py
utils/dir.py
utils/dir_compression.py
utils/dir_search.py
utils/exiftool.py
utils/file.py
utils/file_compression.py
utils/file_convert.py
utils/file_image.py
utils/file_read.py
utils/file_search.py
utils/file_write.py
utils/objectUtils.py
utils/resources.py
utils/string_utils.py
colemen_file_utils-1.16.51.dist-info/METADATA
colemen_file_utils-1.16.51.dist-info/WHEEL
colemen_file_utils-1.16.51.dist-info/top_level.txt
colemen_file_utils-1.16.51.dist-info/RECORD
