Metadata-Version: 2.1
Name: colemen-file-utils
Version: 1.16.51
Summary: Colemen File Utils
Home-page: UNKNOWN
Author: Colemen Atwood
Author-email: <atwoodcolemen@gmail.com>
License: UNKNOWN
Keywords: python
Platform: UNKNOWN
Classifier: Development Status :: 3 - Alpha
Classifier: Intended Audience :: Education
Classifier: Programming Language :: Python :: 2
Classifier: Programming Language :: Python :: 3
Classifier: Operating System :: MacOS :: MacOS X
Classifier: Operating System :: Microsoft :: Windows
Requires-Dist: secure-delete
Requires-Dist: ftputil
Requires-Dist: colemen-string-utils
Requires-Dist: ffmpeg-python
Requires-Dist: pillow
Requires-Dist: iptcinfo3
Requires-Dist: patool
Requires-Dist: pyparsing
